speech_mcp/__init__.py
speech_mcp/__main__.py
speech_mcp/audio_processor.py
speech_mcp/constants.py
speech_mcp/server.py
speech_mcp/speech_recognition.py
speech_mcp/state_manager.py
speech_mcp/streaming_transcriber.py
speech_mcp/config/__init__.py
speech_mcp/resources/__init__.py
speech_mcp/resources/kokoro_tts_adapter.md
speech_mcp/resources/transcription_guide.md
speech_mcp/resources/audio/__init__.py
speech_mcp/resources/audio/start_listening.wav
speech_mcp/resources/audio/stop_listening.wav
speech_mcp/tts_adapters/__init__.py
speech_mcp/tts_adapters/kokoro_adapter.py
speech_mcp/tts_adapters/pyttsx3_adapter.py
speech_mcp/ui/__init__.py
speech_mcp/ui/__main__.py
speech_mcp/ui/components/__init__.py
speech_mcp/ui/components/animated_button.py
speech_mcp/ui/components/audio_processor_ui.py
speech_mcp/ui/components/audio_visualizer.py
speech_mcp/ui/components/tts_adapter.py
speech_mcp/ui/pyqt/__init__.py
speech_mcp/ui/pyqt/__main__.py
speech_mcp/ui/pyqt/pyqt_ui.py
speech_mcp/utils/__init__.py
speech_mcp/utils/logger.py
speech_mcp-1.1.1.dist-info/METADATA
speech_mcp-1.1.1.dist-info/WHEEL
speech_mcp-1.1.1.dist-info/entry_points.txt
speech_mcp-1.1.1.dist-info/RECORD
