Metadata-Version: 2.4
Name: speech-mcp
Version: 1.1.1
Summary: Speech MCP Server with command-line interface and Kokoro TTS support
Requires-Python: >=3.10
Requires-Dist: faster-whisper>=0.10.0
Requires-Dist: ffmpeg>=1.4
Requires-Dist: kokoro>=0.8.4
Requires-Dist: mcp[cli]>=1.2.0
Requires-Dist: misaki[en]
Requires-Dist: numba>=0.57.0
Requires-Dist: numpy>=1.24.0
Requires-Dist: pip
Requires-Dist: psutil>=5.9.0
Requires-Dist: pyaudio>=0.2.13
Requires-Dist: pydantic<3.0.0,>=2.7.2
Requires-Dist: pydub>=0.25.1
Requires-Dist: pyqt5>=5.15.0
Requires-Dist: pyttsx3>=2.90
Requires-Dist: soundfile>=0.12.1
Requires-Dist: speechrecognition>=3.10.0
Requires-Dist: torch
Provides-Extra: all
Requires-Dist: misaki[ja]; extra == 'all'
Requires-Dist: misaki[zh]; extra == 'all'
Provides-Extra: ja
Requires-Dist: misaki[ja]; extra == 'ja'
Provides-Extra: zh
Requires-Dist: misaki[zh]; extra == 'zh'
